[
    {
        "title":"Why We Use <br> Element",
        "answer_1":"To Make Text Bold",
        "answer_2":"To Make Text Italic",
        "answer_3":"To add Breakline",
        "answer_4":"To Create Harizontal Line",
        "right_answer":"To add Breakline"
    },
    {
        "title":"Is <img> Element Has Attribute href",
        "answer_1":"Yes",
        "answer_2":"No Its Fot Tag <a>",
        "answer_3":"All Element Has This Atribute",
        "answer_4":"No <img> Element Has Atribute src",
        "right_answer":"No <img> Element Has Atribute src"
    },
    {
        "title":"How Can We Make Element Text Bold",
        "answer_1":"Putting It Inside <b> Tag ",
        "answer_2":"Putting It Inside <strong> Tag ",
        "answer_3":"Font-Weight Property In Css",
        "answer_4":"All Answer Is Right",
        "right_answer":"All Answer Is Right"
    },
    {
        "title":"What Is The Right Hierarchy For Creating Part Of Page",
        "answer_1":"<h1>Then<p>Then<h2>Then<h3>Then<p>Then<img>",
        "answer_2":"<h1>Then<p>Then<h3>Then<p>Then<h2>Then<img>",
        "answer_3":"<p>Then<h1>Then<h2>Then<h3>Then<p>Then<img>",
        "answer_4":"All Answer Is Wrong",
        "right_answer":"All Answer Is Wrong"
    },
    {
        "title":"How Can WE Include Externale Page Inside Our HTML Page",
        "answer_1":"By Using Include in HTML",
        "answer_2":"By Using Load in HTML",
        "answer_3":"By Using Iframe Tag",
        "answer_4":"All Solution Is Wrong",
        "right_answer":"By Using Iframe Tag"
    },
    {
        "title":"What Is The Tag That Not Exists in HTML",
        "answer_1":"<object>",
        "answer_2":"<abrr>",
        "answer_3":"<basefont>",
        "answer_4":"All Tag Is Exists in HTML",
        "right_answer":"<basefont>"
    },
    {
        "title":"What Is The Element That Not Exists In HTML5 Semantics",
        "answer_1":"<article>",
        "answer_2":"<section>",
        "answer_3":"<blockquote>",
        "answer_4":"<aside>",
        "right_answer":"<blockquote>"
    },
    {
        "title":"In HTML Can We Use this Way To Add Attributes",
        "answer_1":"<div class='class-name'></div>",
        "answer_2":"<div class=\"class-name\"></div>",
        "answer_3":"<div class=class-name></div>",
        "answer_4":"All Is Right",
        "right_answer":"<div class=\"class-name\"></div>"
    },
    {
        "title":"How Can We Specify Document Type Of HTML5 Page",
        "answer_1":"<DOCTYPE html>",
        "answer_2":"<DOCTYPE html5>",
        "answer_3":"<!DOCTYPE html>",
        "answer_4":"<DOCTYPE html!>",
        "right_answer":"<!DOCTYPE html>"
    },
    {
        "title":"Why We Use HTML",
        "answer_1":"To Make Application",
        "answer_2":"To Buld a Web Site",
        "answer_3":"To Create a Video Game",
        "answer_4":"All Answer Is Right",
        "right_answer":"To Buld a Web Site"
    }

]